eztest/__init__.py
eztest/_funccase.py
eztest/calc_report.py
eztest/ini.py
eztest/mail.py
eztest/report.py
eztest/stringbuilder.py
eztest/testcase.py
eztest/testmode.py
eztest/utility.py
eztest-2.0.1.dist-info/DESCRIPTION.rst
eztest-2.0.1.dist-info/METADATA
eztest-2.0.1.dist-info/RECORD
eztest-2.0.1.dist-info/WHEEL
eztest-2.0.1.dist-info/entry_points.txt
eztest-2.0.1.dist-info/metadata.json
eztest-2.0.1.dist-info/top_level.txt
