Metadata-Version: 2.0
Name: eztest
Version: 2.0.1
Summary: eztest is a Python package and execution used for performance testing or load testing.
Home-page: https://github.com/lgt1001/eztest
Author: lgt
Author-email: lgt.1001-@163.com
Maintainer: lgt
Maintainer-email: lgt.1001-@163.com
License: GPL
Download-URL: https://github.com/lgt1001/eztest
Keywords: performance load test testing performance-test load-test performance-testing load-testing
Platform: Windows
Platform: MacOS
Platform: Unix
Platform: Linux
Classifier: Development Status :: 4 - Beta
Classifier: License :: OSI Approved :: GNU General Public License (GPL)
Classifier: Programming Language :: Python :: 2.7
Classifier: Programming Language :: Python :: 3.2
Classifier: Programming Language :: Python :: 3.3
Classifier: Programming Language :: Python :: 3.4
Classifier: Programming Language :: Python :: 3.5
Classifier: Programming Language :: Python :: 3.6
Classifier: Programming Language :: Python :: 3.7
Classifier: Operating System :: MacOS :: MacOS X
Classifier: Operating System :: Microsoft :: Windows
Classifier: Operating System :: POSIX
Classifier: Operating System :: Unix
Classifier: Topic :: Software Development :: Testing
Classifier: Topic :: Software Development :: Libraries
Classifier: Intended Audience :: Developers
Requires-Dist: psutil
